odoo/addons/account_reports_hide_ref/LICENSE
odoo/addons/account_reports_hide_ref/README.rst
odoo/addons/account_reports_hide_ref/__init__.py
odoo/addons/account_reports_hide_ref/__manifest__.py
odoo/addons/account_reports_hide_ref/images/screen.png
odoo/addons/account_reports_hide_ref/models/__init__.py
odoo/addons/account_reports_hide_ref/models/account_general_ledger.py
odoo/addons/account_reports_hide_ref/static/description/icon.png
odoo/addons/account_reports_hide_ref/static/description/index.html
odoo_addon_account_reports_hide_ref-18.0.1.0.0.dist-info/METADATA
odoo_addon_account_reports_hide_ref-18.0.1.0.0.dist-info/WHEEL
odoo_addon_account_reports_hide_ref-18.0.1.0.0.dist-info/top_level.txt
odoo_addon_account_reports_hide_ref-18.0.1.0.0.dist-info/RECORD
