Metadata-Version: 2.1
Name: odoo-addon-account_reports_hide_ref
Version: 18.0.1.0.0
Requires-Python: >=3.10
Requires-Dist: odoo==18.0.*
Summary: Hide journal post ref in general ledger report.
Home-page: https://www.mint-system.ch/
License: OPL-1
Author: Mint System GmbH
Classifier: Programming Language :: Python
Classifier: Framework :: Odoo
Classifier: Framework :: Odoo :: 18.0
